code_analysis/__init__.py
code_analysis/configure.py
code_analysis/re_statement.py
GITCodeAnalysis-1.0.2.dist-info/LICENSE
GITCodeAnalysis-1.0.2.dist-info/METADATA
GITCodeAnalysis-1.0.2.dist-info/WHEEL
GITCodeAnalysis-1.0.2.dist-info/top_level.txt
GITCodeAnalysis-1.0.2.dist-info/RECORD
